kivyauth/__init__.py
kivyauth/facebook_auth.py
kivyauth/github_auth.py
kivyauth/google_auth.py
kivyauth/twitter_auth.py
kivyauth/utils.py
kivyauth/android/__init__.py
kivyauth/android/facebook_auth.py
kivyauth/android/firebase_auth.py
kivyauth/android/github_auth.py
kivyauth/android/google_auth.py
kivyauth/android/twitter_auth.py
kivyauth/desktop/__init__.py
kivyauth/desktop/facebook_auth.py
kivyauth/desktop/github_auth.py
kivyauth/desktop/google_auth.py
kivyauth/desktop/twitter_auth.py
kivyauth/desktop/utils.py
KivyAuth-2.3.3.dist-info/LICENSE
KivyAuth-2.3.3.dist-info/METADATA
KivyAuth-2.3.3.dist-info/WHEEL
KivyAuth-2.3.3.dist-info/top_level.txt
KivyAuth-2.3.3.dist-info/RECORD
