Metadata-Version: 2.1
Name: KivyAuth
Version: 2.3.3
Summary: Integrate Google, Facebook, Github & Twitter login in kivy applications 
Home-page: https://github.com/shashi278/social-auth-kivy
Author: Shashi Ranjan
Author-email: shashiranjankv@gmail.com
Keywords: social-login google-login facebook-login firebase-auth kivy-application kivy python
Classifier: Programming Language :: Python :: 3
Classifier: License :: OSI Approved :: MIT License
Classifier: Operating System :: Android
Classifier: Operating System :: Microsoft :: Windows
Classifier: Operating System :: OS Independent
Requires-Python: >=3.6
License-File: LICENSE
Requires-Dist: kivy (>=2.0.0)
Requires-Dist: oauthlib
Requires-Dist: werkzeug (==2.0.3)
Requires-Dist: flask (==2.0.3)
Requires-Dist: requests
